pgbouncer/__init__.py
pgbouncer/fixture.py
pgbouncer/tests.py
pgbouncer-0.1.0.dist-info/LICENSE
pgbouncer-0.1.0.dist-info/METADATA
pgbouncer-0.1.0.dist-info/WHEEL
pgbouncer-0.1.0.dist-info/top_level.txt
pgbouncer-0.1.0.dist-info/RECORD
