Metadata-Version: 2.1
Name: pgbouncer
Version: 0.1.0
Summary: Fixture to bring up temporary pgbouncer instance.
Home-page: https://launchpad.net/python-pgbouncer
Maintainer: Launchpad Developers
Maintainer-email: launchpad-dev@lists.launchpad.net
Classifier: Development Status :: 4 - Beta
Classifier: Intended Audience :: Developers
Classifier: License :: OSI Approved :: GNU Affero General Public License v3
Classifier: Operating System :: OS Independent
Classifier: Programming Language :: Python
Classifier: Programming Language :: Python :: 3
Classifier: Programming Language :: Python :: 3.5
Classifier: Programming Language :: Python :: 3.6
Classifier: Programming Language :: Python :: 3.7
Classifier: Programming Language :: Python :: 3.8
Classifier: Programming Language :: Python :: 3.9
Classifier: Programming Language :: Python :: 3.10
Classifier: Programming Language :: Python :: 3.11
Classifier: Programming Language :: Python :: 3.12
Classifier: Programming Language :: Python :: 3.13
Requires-Python: >=3.5
License-File: LICENSE
Requires-Dist: fixtures
Requires-Dist: psycopg2
Requires-Dist: testtools
Provides-Extra: test
Requires-Dist: postgresfixture ; extra == 'test'
Requires-Dist: testscenarios ; extra == 'test'
